MANIFEST.in
README.rst
setup.py
tgext/__init__.py
tgext.mailer.egg-info/PKG-INFO
tgext.mailer.egg-info/SOURCES.txt
tgext.mailer.egg-info/dependency_links.txt
tgext.mailer.egg-info/entry_points.txt
tgext.mailer.egg-info/namespace_packages.txt
tgext.mailer.egg-info/not-zip-safe
tgext.mailer.egg-info/requires.txt
tgext.mailer.egg-info/top_level.txt
tgext/mailer/__init__.py
tgext/mailer/_compat.py
tgext/mailer/exceptions.py
tgext/mailer/mailer.py
tgext/mailer/message.py
tgext/mailer/plugmailer.py