Metadata-Version: 1.1
Name: tgext.mailer
Version: 0.2.0
Summary: TurboGears extension for sending emails with transaction manager integration
Home-page: https://github.com/amol-/tgext.mailer
Author: Alessandro Molina
Author-email: amol@turbogears.org
License: MIT
Keywords: turbogears2.extension
Platform: UNKNOWN
Classifier: Environment :: Web Environment
Classifier: Framework :: TurboGears
